keenmail_mcp/__init__.py
keenmail_mcp/__main__.py
keenmail_mcp/config.py
keenmail_mcp/openapi.py
keenmail_mcp/server.py
keenmail_mcp_server-0.1.6.dist-info/METADATA
keenmail_mcp_server-0.1.6.dist-info/WHEEL
keenmail_mcp_server-0.1.6.dist-info/entry_points.txt
keenmail_mcp_server-0.1.6.dist-info/licenses/LICENSE
keenmail_mcp_server-0.1.6.dist-info/RECORD
