Metadata-Version: 2.4
Name: keenmail-mcp-server
Version: 0.1.6
Summary: MCP server for KeenMail API integration
Project-URL: Homepage, https://github.com/optimoz-inc/keenmail-mcp-server
Project-URL: Repository, https://github.com/optimoz-inc/keenmail-mcp-server
Project-URL: Issues, https://github.com/optimoz-inc/keenmail-mcp-server/issues
Project-URL: Organization, https://optimoz.com
Author-email: Renesa Patel <renesa@optimoz.com>
License: MIT
License-File: LICENSE
Keywords: api,email,keenmail,mcp,server
Classifier: Development Status :: 4 - Beta
Classifier: Intended Audience :: Developers
Classifier: License :: OSI Approved :: MIT License
Classifier: Programming Language :: Python :: 3
Classifier: Programming Language :: Python :: 3.10
Classifier: Programming Language :: Python :: 3.11
Classifier: Programming Language :: Python :: 3.12
Classifier: Topic :: Communications :: Email
Classifier: Topic :: Software Development :: Libraries :: Python Modules
Requires-Python: >=3.10
Requires-Dist: fastmcp>=0.1.0
Requires-Dist: httpx>=0.24.0
Requires-Dist: pydantic>=2.0.0
Provides-Extra: dev
Requires-Dist: mypy>=1.5.0; extra == 'dev'
Requires-Dist: pytest-asyncio>=0.21.0; extra == 'dev'
Requires-Dist: pytest>=7.0.0; extra == 'dev'
Requires-Dist: ruff>=0.1.0; extra == 'dev'
